{
  "attrs": [
    {
      "is_compare": true,
      "name": "Requirements specification",
      "value": "lib:idr"
    },
    {
      "is_compare": true,
      "name": "Program fragment",
      "value": "ext-modules/linux/lib/idr/destroy-before-usage.ko"
    }
  ],
  "description": "",
  "error_trace": [
    [
      [
        {
          "EMG wrapper": [
            {
              "LDV model 'init'": [
                {
                  "Instrumented function 'idr_init'": [
                    {
                      "LDV model 'idr_init_idp'": []
                    }
                  ]
                },
                {
                  "Instrumented function 'idr_destroy'": [
                    {
                      "LDV model 'idr_destroy_idp'": []
                    }
                  ]
                },
                {
                  "Instrumented function 'idr_alloc'": [
                    {
                      "LDV model 'idr_alloc_idp'": [
                        {
                          "LDV model 'assert'": []
                        }
                      ]
                    }
                  ]
                }
              ]
            }
          ]
        }
      ]
    ]
  ],
  "function": "thread_call_forests",
  "is_modifiable": false,
  "status": null,
  "tags": [],
  "threshold": 0,
  "verdict": "2"
}