{
  "attrs": [
    {
      "is_compare": true,
      "name": "Requirements specification",
      "value": "lib:idr"
    },
    {
      "is_compare": true,
      "name": "Program fragment",
      "value": "ext-modules/linux/lib/idr/more-at-exit.ko"
    }
  ],
  "description": "",
  "error_trace": [
    [
      [
        {
          "Entry point 'main'": [
            {
              "LDV model 'check_final_state'": []
            }
          ]
        }
      ]
    ],
    [
      [
        {
          "EMG wrapper": [
            {
              "LDV model 'init'": [
                {
                  "Instrumented function 'idr_init'": [
                    {
                      "LDV model 'idr_init_idp'": []
                    }
                  ]
                }
              ]
            }
          ]
        }
      ]
    ]
  ],
  "function": "thread_call_forests",
  "is_modifiable": false,
  "status": null,
  "tags": [],
  "threshold": 100,
  "verdict": "2"
}