{
  "attrs": [
    {
      "is_compare": true,
      "name": "Linux:Version",
      "value": "v3.16.3-146-g5294e5fe7064"
    },
    {
      "is_compare": true,
      "name": "Requirements specification",
      "value": "drivers:clk2"
    },
    {
      "is_compare": true,
      "name": "Program fragment",
      "value": "drivers/usb/dwc2/dwc2_gadget.ko"
    }
  ],
  "description": "Target bug.",
  "error_trace": [
    [
      {
        "s3c_hsotg_probe": [
          {
            "ldv_clk_disable_clk_of_s3c_hsotg": [
              {
                "ldv_assert_linux_drivers_clk2__less_initial_decrement": []
              }
            ]
          }
        ]
      }
    ]
  ],
  "function": "thread_call_forests",
  "is_modifiable": true,
  "tags": [],
  "verdict": "2"
}