{
  "attrs": [
    {
      "is_compare": true,
      "name": "Program fragment",
      "value": "ext-modules/linux/memory-safety/memset4.ko"
    },
    {
      "is_compare": true,
      "name": "Requirements specification",
      "value": "memory safety"
    }
  ],
  "description": "CPAchecker SMG does not support setting non-zero values to non-char variables/fields by means of memset().",
  "error_trace": [
    [
      [
        {
          "EMG wrapper": [
            {
              "LDV model 'init'": []
            }
          ]
        }
      ]
    ]
  ],
  "function": "thread_call_forests",
  "is_modifiable": false,
  "status": null,
  "tags": [
    "Verifier",
    "Verifier - CPAchecker SMG"
  ],
  "threshold": 100,
  "verdict": "3"
}