{
  "attrs": [
    {
      "is_compare": true,
      "name": "Declaration",
      "value": "struct ldv_struct (?.a)"
    },
    {
      "is_compare": true,
      "name": "Requirements specification",
      "value": "concurrency safety"
    },
    {
      "is_compare": true,
      "name": "Program fragment",
      "value": "ext-modules/linux/concurrency-safety/unsorted/lockTest-unsafe.ko"
    }
  ],
  "description": "",
  "error_trace": [
    [
      [
        {
          "EMG wrapper": [
            {
              "init": [
                {
                  "LDV model 'main'": [
                    {
                      "LDV model 'func'": [
                        {
                          "Instrumented function 'mutex_lock'": []
                        },
                        {
                          "Instrumented function 'mutex_lock'": []
                        },
                        {
                          "Instrumented function 'mutex_unlock'": []
                        },
                        {
                          "Instrumented function 'mutex_unlock'": []
                        }
                      ]
                    }
                  ]
                }
              ]
            }
          ]
        }
      ]
    ],
    [
      [
        {
          "LDV model 'main'": [
            {
              "LDV model 'func'": [
                {
                  "Instrumented function 'mutex_lock'": []
                },
                {
                  "Instrumented function 'mutex_lock'": []
                },
                {
                  "Instrumented function 'mutex_unlock'": []
                },
                {
                  "Instrumented function 'mutex_unlock'": []
                }
              ]
            }
          ]
        }
      ]
    ]
  ],
  "function": "thread_call_forests",
  "is_modifiable": true,
  "status": null,
  "tags": [],
  "threshold": 100,
  "verdict": "2"
}