{
  "attrs": [
    {
      "is_compare": true,
      "name": "Requirements specification",
      "value": "alloc:spinlock"
    },
    {
      "is_compare": true,
      "name": "Program fragment",
      "value": "ext-modules/linux/alloc/spinlock/nonatomic-lock.ko"
    }
  ],
  "description": "",
  "error_trace": [
    [
      {
        "ldv_init": [
          {
            "ldv_spin_lock_45": [
              {
                "ldv_spin_lock_ldv_lock": []
              }
            ]
          },
          {
            "ldv_check_alloc_nonatomic": [
              {
                "ldv_exclusive_spin_is_locked": []
              },
              {
                "ldv_assert_linux_alloc_spinlock__nonatomic": []
              }
            ]
          }
        ]
      }
    ]
  ],
  "function": "thread_call_forests",
  "is_modifiable": true,
  "tags": [],
  "verdict": "2"
}