{
  "attrs": [
    {
      "is_compare": true,
      "name": "Project:Version",
      "value": "v5.12-rc2-286-gdd4fa1dae9f4"
    },
    {
      "is_compare": true,
      "name": "Program fragment",
      "value": "drivers/net/ethernet/marvell/pxa168_eth.ko"
    },
    {
      "is_compare": true,
      "name": "Requirements specification",
      "value": "concurrency safety"
    },
    {
      "is_compare": true,
      "name": "Declaration",
      "value": "struct pxa168_eth_private (?.work_todo)"
    }
  ],
  "description": "Likely pxa168_eth_start_xmit()/pxa168_eth_netpoll() should not be invoked after napi_disable() and netif_carrier_off().",
  "error_trace": [
    [
      [
        {
          "EMG wrapper": [
            {
              "pxa168_eth_stop": [
                {
                  "txq_deinit": [
                    {
                      "txq_reclaim": [
                        {
                          "netif_tx_lock": [
                            {
                              "Instrumented function 'spin_lock'": []
                            }
                          ]
                        }
                      ]
                    }
                  ]
                }
              ]
            }
          ]
        }
      ]
    ],
    [
      [
        {
          "EMG wrapper": [
            {
              "pxa168_eth_netpoll": [
                {
                  "pxa168_eth_int_handler": [
                    {
                      "pxa168_eth_collect_events": []
                    }
                  ]
                }
              ]
            }
          ]
        }
      ]
    ]
  ],
  "function": "thread_call_forests",
  "is_modifiable": false,
  "status": null,
  "tags": [
    "EMG - Specs",
    "EMG"
  ],
  "threshold": 100,
  "verdict": "3"
}