{
  "Klever Addons": {
    "CIF": {
      "version": "a451e44",
      "path": "https://forge.ispras.ru/attachments/download/8050/cif-a451e44.tar.xz",
      "executable path": "bin"
    },
    "CIL": {
      "version": "688024c",
      "path": "https://forge.ispras.ru/attachments/download/8049/frama-c-cil-688024c.tar.xz",
      "executable path": "."
    },
    "Consul": {
      "version": "0.9.2",
      "path": "https://releases.hashicorp.com/consul/0.9.2/consul_0.9.2_linux_amd64.zip",
      "executable path": "consul"
    },
    "Verification Backends": {
      "CPAchecker": {
        "name": "CPAchecker",
        "version": "trunk:31140",
        "path": "https://forge.ispras.ru/attachments/download/6427/CPAchecker-1.8-svn 31140-unix.tar.xz",
        "executable path": "scripts"
      },
      "CPALockator": {
        "name": "CPAchecker",
        "version": "CPALockator-combat-mode:34860",
        "path": "https://forge.ispras.ru/attachments/download/7881/CPAchecker-1.8-svn-34860-unix.tar.xz",
        "executable path": "scripts"
      }
    }
  },
  "Klever Build Bases": {
    "linux/loadable kernel modules sample": {
      "path": "https://forge.ispras.ru/attachments/download/8016/build-base-linux-3.14.79-x86_64-sample.tar.xz"
    }
  }
}
