{
  "attrs": [
    {
      "attr": "Klever Core version",
      "is_compare": false,
      "value": "1.1.dev147+g040570141"
    },
    {
      "attr": "Sub-job identifier",
      "is_compare": false,
      "value": "36"
    },
    {
      "attr": "Linux kernel:Version",
      "is_compare": false,
      "value": "3.14.0"
    },
    {
      "attr": "Linux kernel:Architecture",
      "is_compare": false,
      "value": "x86_64"
    },
    {
      "attr": "Linux kernel:Configuration",
      "is_compare": false,
      "value": "allmodconfig"
    },
    {
      "attr": "LKVOG strategy:Name",
      "is_compare": false,
      "value": "separate modules"
    },
    {
      "attr": "Requirement",
      "is_compare": true,
      "value": "linux:concurrency safety"
    },
    {
      "attr": "Verification object",
      "is_compare": true,
      "value": "ext-modules/linux/concurrency-safety/unsorted/FunctionPointerTest-unsafe.ko"
    },
    {
      "attr": "Declaration",
      "is_compare": false,
      "value": "struct ldv_struct *(?.field1)"
    },
    {
      "attr": "Refinement-status",
      "is_compare": false,
      "value": "Confirmed"
    }
  ],
  "comparison": "thread_call_forests",
  "description": "",
  "error trace": [
    [
      {
        "ldv_init": [
          {
            "ldv_func": []
          }
        ]
      }
    ],
    [
      {
        "ldv_locker": [
          {
            "ldv_mutex_lock_39": []
          }
        ]
      }
    ]
  ],
  "is_modifiable": false,
  "status": "1",
  "tags": [],
  "verdict": "2"
}