{
  "attrs": [
    {
      "attr": "Klever Core version",
      "is_compare": false,
      "value": "1.1.dev147+g040570141"
    },
    {
      "attr": "Sub-job identifier",
      "is_compare": false,
      "value": "36"
    },
    {
      "attr": "Linux kernel:Version",
      "is_compare": false,
      "value": "3.14.0"
    },
    {
      "attr": "Linux kernel:Architecture",
      "is_compare": false,
      "value": "x86_64"
    },
    {
      "attr": "Linux kernel:Configuration",
      "is_compare": false,
      "value": "allmodconfig"
    },
    {
      "attr": "LKVOG strategy:Name",
      "is_compare": false,
      "value": "separate modules"
    },
    {
      "attr": "Rule specification",
      "is_compare": true,
      "value": "sync:race"
    },
    {
      "attr": "Verification object",
      "is_compare": true,
      "value": "ext-modules/sync/race/unsorted/lockTest-unsafe.ko"
    },
    {
      "attr": "Declaration",
      "is_compare": true,
      "value": "struct ldv_struct *&(?.a)"
    },
    {
      "attr": "Refinement-status",
      "is_compare": false,
      "value": "Confirmed"
    }
  ],
  "comparison": "thread_call_forests",
  "description": "",
  "error trace": [
    [
      {
        "init": [
          {
            "ldv_main": [
              {
                "ldv_func": [
                  {
                    "ldv_mutex_lock_27": []
                  },
                  {
                    "ldv_mutex_lock_28": []
                  },
                  {
                    "ldv_mutex_unlock_29": []
                  },
                  {
                    "ldv_mutex_unlock_30": []
                  }
                ]
              },
              {
                "ldv_mutex_lock_31": []
              },
              {
                "ldv_mutex_unlock_32": []
              }
            ]
          }
        ]
      }
    ],
    [
      {
        "ldv_main": [
          {
            "ldv_func": [
              {
                "ldv_mutex_lock_27": []
              },
              {
                "ldv_mutex_lock_28": []
              },
              {
                "ldv_mutex_unlock_29": []
              },
              {
                "ldv_mutex_unlock_30": []
              }
            ]
          },
          {
            "ldv_mutex_lock_31": []
          }
        ]
      }
    ]
  ],
  "is_modifiable": false,
  "status": "1",
  "tags": [],
  "verdict": "2"
}